{
  "version": "7",
  "dialect": "postgresql",
  "entries": [
    {
      "idx": 0,
      "version": "7",
      "when": 1733408170427,
      "tag": "0000_foamy_millenium_guard",
      "breakpoints": true
    },
    {
      "idx": 1,
      "version": "7",
      "when": 1733408538207,
      "tag": "0001_vengeful_human_robot",
      "breakpoints": true
    },
    {
      "idx": 2,
      "version": "7",
      "when": 1733409128950,
      "tag": "0002_zippy_silverclaw",
      "breakpoints": true
    },
    {
      "idx": 3,
      "version": "7",
      "when": 1733466156950,
      "tag": "0003_breezy_komodo",
      "breakpoints": true
    },
    {
      "idx": 4,
      "version": "7",
      "when": 1733503951029,
      "tag": "0004_chunky_lyja",
      "breakpoints": true
    },
    {
      "idx": 5,
      "version": "7",
      "when": 1733503986924,
      "tag": "0005_silky_azazel",
      "breakpoints": true
    }
  ]
}